merge_fastq/__init__.py
merge_fastq/cli.py
merge_fastq/merge_fastq.py
merge_fastq-0.1.7.dist-info/AUTHORS.rst
merge_fastq-0.1.7.dist-info/LICENSE
merge_fastq-0.1.7.dist-info/METADATA
merge_fastq-0.1.7.dist-info/WHEEL
merge_fastq-0.1.7.dist-info/entry_points.txt
merge_fastq-0.1.7.dist-info/top_level.txt
merge_fastq-0.1.7.dist-info/RECORD
