Metadata-Version: 2.1
Name: merge-fastq
Version: 0.1.7
Summary: Package to merge multiple pair of pair-end fastq data
Home-page: https://github.com/rhshah/merge_fastq
Author: Ronak Shah
Author-email: rons.shah@gmail.com
License: Apache Software License 2.0
Keywords: merge_fastq
Platform: UNKNOWN
Classifier: Development Status :: 2 - Pre-Alpha
Classifier: Intended Audience :: Developers
Classifier: License :: OSI Approved :: Apache Software License
Classifier: Natural Language :: English
Classifier: Programming Language :: Python :: 3.7
Requires-Python: >=3.7, !=3.0.*, !=3.1.*, !=3.2.*, !=3.3.*, !=3.4.*
Requires-Dist: Click (==7.0)
Requires-Dist: click-log (==0.3.2)
